nerdfont_fetcher/__init__.py
nerdfont_fetcher/cli.py
nerdfont_fetcher/data_source.py
nerdfont_fetcher/font_manager.py
nerdfont_fetcher-0.1.0.dist-info/LICENSE
nerdfont_fetcher-0.1.0.dist-info/METADATA
nerdfont_fetcher-0.1.0.dist-info/WHEEL
nerdfont_fetcher-0.1.0.dist-info/entry_points.txt
nerdfont_fetcher-0.1.0.dist-info/RECORD
