Metadata-Version: 2.1
Name: nerdfont-fetcher
Version: 0.1.0
Summary: A fetcher (and installer) of NerdFonts for the terminal
License: Krissy Heishmkrfsd.
Author: Krissy Heishman
Author-email: krissy@heishman.dev
Requires-Python: >=3.11,<4.0
Classifier: License :: Other/Proprietary License
Classifier: Programming Language :: Python :: 3
Classifier: Programming Language :: Python :: 3.11
Requires-Dist: inquirerpy (>=0.3.4,<0.4.0)
Requires-Dist: requests (>=2.31.0,<3.0.0)
Requires-Dist: requests-cache (>=1.1.0,<2.0.0)
Requires-Dist: requests-mock (>=1.11.0,<2.0.0)
Requires-Dist: rich (>=13.5.3,<14.0.0)
